brapy/main.py
brapy-0.0.1.dist-info/LICENCE
brapy-0.0.1.dist-info/METADATA
brapy-0.0.1.dist-info/WHEEL
brapy-0.0.1.dist-info/RECORD
