Metadata-Version: 2.1
Name: brapy
Version: 0.0.1
Summary: Python client to acess brapi.dev
Author: Vinealius
Author-email: lucas_vinicius10@live.com
Requires-Python: >=3.10,<4.0
Classifier: Programming Language :: Python :: 3
Classifier: Programming Language :: Python :: 3.10
Classifier: Programming Language :: Python :: 3.11
Classifier: Programming Language :: Python :: 3.12
Requires-Dist: SQLAlchemy (>=2.0.27,<3.0.0)
Requires-Dist: alembic (>=1.13.1,<2.0.0)
Requires-Dist: httpx (>=0.27.0,<0.28.0)
